turtleTello/__init__.py
turtleTello/tello.py
turtleTello-2.6.dist-info/License.txt
turtleTello-2.6.dist-info/METADATA
turtleTello-2.6.dist-info/WHEEL
turtleTello-2.6.dist-info/top_level.txt
turtleTello-2.6.dist-info/RECORD
